odoo/addons/sale_order_mass_action/README.rst
odoo/addons/sale_order_mass_action/__init__.py
odoo/addons/sale_order_mass_action/__manifest__.py
odoo/addons/sale_order_mass_action/i18n/fr.po
odoo/addons/sale_order_mass_action/i18n/sale_order_mass_action.pot
odoo/addons/sale_order_mass_action/readme/CONTRIBUTORS.rst
odoo/addons/sale_order_mass_action/readme/DESCRIPTION.rst
odoo/addons/sale_order_mass_action/readme/ROADMAP.rst
odoo/addons/sale_order_mass_action/readme/USAGE.rst
odoo/addons/sale_order_mass_action/security/security.xml
odoo/addons/sale_order_mass_action/static/description/icon.png
odoo/addons/sale_order_mass_action/static/description/index.html
odoo/addons/sale_order_mass_action/tests/__init__.py
odoo/addons/sale_order_mass_action/tests/test_sale_order_mass_action.py
odoo/addons/sale_order_mass_action/wizards/__init__.py
odoo/addons/sale_order_mass_action/wizards/sale_order_mass_action_view.xml
odoo/addons/sale_order_mass_action/wizards/sale_order_mass_action_wizard.py
odoo_addon_sale_order_mass_action-16.0.1.0.0.4.dist-info/METADATA
odoo_addon_sale_order_mass_action-16.0.1.0.0.4.dist-info/WHEEL
odoo_addon_sale_order_mass_action-16.0.1.0.0.4.dist-info/top_level.txt
odoo_addon_sale_order_mass_action-16.0.1.0.0.4.dist-info/RECORD
